genobjdet/__init__.py
genobjdet/isolate_library.py
genobjdet-0.1.8.dist-info/LICENSE
genobjdet-0.1.8.dist-info/METADATA
genobjdet-0.1.8.dist-info/WHEEL
genobjdet-0.1.8.dist-info/top_level.txt
genobjdet-0.1.8.dist-info/RECORD
