Metadata-Version: 2.1
Name: genobjdet
Version: 0.1.8
Summary: A package for isolating objects in images
Author: Brayden Levangie
Classifier: Programming Language :: Python :: 3
Classifier: License :: OSI Approved :: MIT License
Classifier: Operating System :: OS Independent
License-File: LICENSE
Requires-Dist: opencv-python
Requires-Dist: requests
